Better_Console/__init__.py
Better_Console-0.0.6.dist-info/LICENSE
Better_Console-0.0.6.dist-info/METADATA
Better_Console-0.0.6.dist-info/WHEEL
Better_Console-0.0.6.dist-info/top_level.txt
Better_Console-0.0.6.dist-info/RECORD
